vptree.py
vptree-1.0.2.dist-info/DESCRIPTION.rst
vptree-1.0.2.dist-info/METADATA
vptree-1.0.2.dist-info/RECORD
vptree-1.0.2.dist-info/WHEEL
vptree-1.0.2.dist-info/metadata.json
vptree-1.0.2.dist-info/top_level.txt
