Metadata-Version: 2.0
Name: vptree
Version: 1.0.2
Summary: A package implementing a vantage-point data structure, for efficient nearest neighbor searching.
Home-page: https://github.com/RickardSjogren/vptree
Author: Rickard Sjögren
Author-email: r.sjogren89@gmail.com
License: MIT
Keywords: python machine learning search
Platform: UNKNOWN
Classifier: Development Status :: 5 - Production/Stable
Classifier: Intended Audience :: Science/Research
Classifier: Intended Audience :: Developers
Classifier: Intended Audience :: Information Technology
Classifier: License :: OSI Approved :: MIT License
Classifier: Programming Language :: Python :: 2.7
Classifier: Programming Language :: Python :: 3.4
Classifier: Programming Language :: Python :: 3.5
Classifier: Programming Language :: Python :: 3.6
Classifier: Topic :: Scientific/Engineering
Classifier: Topic :: Scientific/Engineering :: Artificial Intelligence
Requires-Dist: numpy
